poetry_t/__init__.py
poetry_t-0.1.3.dist-info/METADATA
poetry_t-0.1.3.dist-info/WHEEL
poetry_t-0.1.3.dist-info/RECORD
